pbi_load_test/__init__.py
pbi_load_test/__main__.py
pbi_load_test/config.py
pbi_load_test/pbi.py
pbi_load_test/scraping.py
pbi_load_test/static/PBIESinglePageUOD_noADAL_event_filter_loop.html
pbi_load_test/static/RealisticLoadTest.html
pbi_load_test-0.1.0.dist-info/METADATA
pbi_load_test-0.1.0.dist-info/WHEEL
pbi_load_test-0.1.0.dist-info/RECORD
