Metadata-Version: 2.1
Name: pbi-load-test
Version: 0.1.0
Summary: 
Author: Léo Grosjean
Author-email: leo.grosjean@servier.com
Requires-Python: >=3.9,<4.0
Classifier: Programming Language :: Python :: 3
Classifier: Programming Language :: Python :: 3.9
Classifier: Programming Language :: Python :: 3.10
Classifier: Programming Language :: Python :: 3.11
Requires-Dist: azure-identity (>=1.14.0,<2.0.0)
Requires-Dist: pyyaml (>=6.0.1,<7.0.0)
Requires-Dist: requests (>=2.31.0,<3.0.0)
Requires-Dist: selenium (>=4.11.2,<5.0.0)
